idplib/Exceptions.py
idplib/HS/DocumentUtils.py
idplib/HS/SubmissionUtils.py
idplib/HS/__init__.py
idplib/Utilities/FuzzyFinder.py
idplib/Utilities/__init__.py
idplib/ValueUtils.py
idplib/__init__.py
idplib/algorithms.py
idplib/defaults.py
idplib-0.0.3.dist-info/LICENSE
idplib-0.0.3.dist-info/METADATA
idplib-0.0.3.dist-info/WHEEL
idplib-0.0.3.dist-info/RECORD
