Metadata-Version: 2.1
Name: idplib
Version: 0.0.3
Summary: IDP Project utility tools
License: MIT
Author: Jack Jorgensen
Author-email: jorgensen.jack@gmail.com
Requires-Python: >=3.7,<4.0
Classifier: License :: OSI Approved :: MIT License
Classifier: Programming Language :: Python :: 3
Classifier: Programming Language :: Python :: 3.7
Classifier: Programming Language :: Python :: 3.8
Classifier: Programming Language :: Python :: 3.9
Classifier: Programming Language :: Python :: 3.10
Classifier: Programming Language :: Python :: 3.11
Classifier: Programming Language :: Python :: 3.12
Requires-Dist: fuzzywuzzy (==0.18.0)
Requires-Dist: python-Levenshtein (==0.20.9)
